<?xml version="1.0" ?>
<list xmlns:xsi="http://www.w3.org/2001/XMLSchema-instance" xsi:noNamespaceSchemaLocation="../../../xsd/optionsData.xsd">
    <option id="24300" name="o_w_84_2s_53">
        <!---->
        <for>
            <add stat="maxMp" val="247.562"/>
            <add stat="rEvas" val="4.675"/>
        </for>
    </option>
    <option id="24301" name="o_w_84_2s_54">
        <!---->
        <for>
            <add stat="maxMp" val="247.562"/>
            <add stat="accCombat" val="3.74"/>
        </for>
    </option>
    <option id="24302" name="o_w_84_2s_55">
        <!---->
        <for>
            <add stat="maxMp" val="247.562"/>
            <add stat="critRate" val="17.6"/>
        </for>
    </option>
    <option id="24303" name="o_w_84_2s_56">
        <!--P. Atk. increases by 78.69. Attack Speed increases by 3.9%-->
        <for>
            <add stat="maxCp" val="311.143"/>
            <add stat="pAtk" val="78.69"/>
            <mul stat="pAtkSpd" val="1.039"/>
        </for>
    </option>
    <option id="24304" name="o_w_84_2s_57">
        <!--M. Atk. increases by 98.96. Casting Speed increases by 4.9%-->
        <for>
            <add stat="maxCp" val="311.143"/>
            <add stat="mAtk" val="98.96"/>
            <mul stat="mAtkSpd" val="1.049"/>
        </for>
    </option>
    <option id="24305" name="o_w_84_2s_58">
        <!---->
        <for>
            <add stat="maxCp" val="311.143"/>
            <add stat="regHp" val="2.74"/>
        </for>
    </option>
    <option id="24306" name="o_w_84_2s_59">
        <!---->
        <for>
            <add stat="maxCp" val="311.143"/>
            <add stat="regMp" val="1.76"/>
        </for>
    </option>
    <option id="24307" name="o_w_84_2s_60">
        <!---->
        <for>
            <add stat="maxCp" val="311.143"/>
            <add stat="regCp" val="2.74"/>
        </for>
    </option>
    <option id="24308" name="o_w_84_2s_61">
        <!---->
        <for>
            <add stat="maxCp" val="311.143"/>
            <add stat="rEvas" val="4.675"/>
        </for>
    </option>
    <option id="24309" name="o_w_84_2s_62">
        <!---->
        <for>
            <add stat="maxCp" val="311.143"/>
            <add stat="accCombat" val="3.74"/>
        </for>
    </option>
    <option id="24310" name="o_w_84_2s_63">
        <!---->
        <for>
            <add stat="maxCp" val="311.143"/>
            <add stat="critRate" val="17.6"/>
        </for>
    </option>
    <option id="24311" name="o_w_84_2s_64">
        <!--P. Atk. increases by 88.53. Attack Speed increases by 4.4% M. Atk. increases by 98.96. Casting Speed increases by 4.9%-->
        <for>
            <add stat="pAtk" val="88.53"/>
            <mul stat="pAtkSpd" val="1.044"/>
            <add stat="mAtk" val="98.96"/>
            <mul stat="mAtkSpd" val="1.049"/>
        </for>
    </option>
    <option id="24312" name="o_w_84_2s_65">
        <!--P. Atk. increases by 88.53. Attack Speed increases by 4.4%-->
        <for>
            <add stat="pAtk" val="88.53"/>
            <mul stat="pAtkSpd" val="1.044"/>
            <add stat="regHp" val="2.74"/>
        </for>
    </option>
    <option id="24313" name="o_w_84_2s_66">
        <!--P. Atk. increases by 88.53. Attack Speed increases by 4.4%-->
        <for>
            <add stat="pAtk" val="88.53"/>
            <mul stat="pAtkSpd" val="1.044"/>
            <add stat="regMp" val="1.76"/>
        </for>
    </option>
    <option id="24314" name="o_w_84_2s_67">
        <!--P. Atk. increases by 88.53. Attack Speed increases by 4.4%-->
        <for>
            <add stat="pAtk" val="88.53"/>
            <mul stat="pAtkSpd" val="1.044"/>
            <add stat="regCp" val="2.74"/>
        </for>
    </option>
    <option id="24315" name="o_w_84_2s_68">
        <!--P. Atk. increases by 88.53. Attack Speed increases by 4.4%-->
        <for>
            <add stat="pAtk" val="88.53"/>
            <mul stat="pAtkSpd" val="1.044"/>
            <add stat="rEvas" val="4.675"/>
        </for>
    </option>
    <option id="24316" name="o_w_84_2s_69">
        <!--P. Atk. increases by 88.53. Attack Speed increases by 4.4%-->
        <for>
            <add stat="pAtk" val="88.53"/>
            <mul stat="pAtkSpd" val="1.044"/>
            <add stat="accCombat" val="3.74"/>
        </for>
    </option>
    <option id="24317" name="o_w_84_2s_70">
        <!--P. Atk. increases by 88.53. Attack Speed increases by 4.4%-->
        <for>
            <add stat="pAtk" val="88.53"/>
            <mul stat="pAtkSpd" val="1.044"/>
            <add stat="critRate" val="17.6"/>
        </for>
    </option>
    <option id="24318" name="o_w_84_2s_71">
        <!--M. Atk. increases by 111.33. Casting Speed increases by 5.6%-->
        <for>
            <add stat="mAtk" val="111.33"/>
            <mul stat="mAtkSpd" val="1.056"/>
            <add stat="regHp" val="2.74"/>
        </for>
    </option>
    <option id="24319" name="o_w_84_2s_72">
        <!--M. Atk. increases by 111.33. Casting Speed increases by 5.6%-->
        <for>
            <add stat="mAtk" val="111.33"/>
            <mul stat="mAtkSpd" val="1.056"/>
            <add stat="regMp" val="1.76"/>
        </for>
    </option>
    <option id="24320" name="o_w_84_2s_73">
        <!--M. Atk. increases by 111.33. Casting Speed increases by 5.6%-->
        <for>
            <add stat="mAtk" val="111.33"/>
            <mul stat="mAtkSpd" val="1.056"/>
            <add stat="regCp" val="2.74"/>
        </for>
    </option>
    <option id="24321" name="o_w_84_2s_74">
        <!--M. Atk. increases by 111.33. Casting Speed increases by 5.6%-->
        <for>
            <add stat="mAtk" val="111.33"/>
            <mul stat="mAtkSpd" val="1.056"/>
            <add stat="rEvas" val="4.675"/>
        </for>
    </option>
    <option id="24322" name="o_w_84_2s_75">
        <!--M. Atk. increases by 111.33. Casting Speed increases by 5.6%-->
        <for>
            <add stat="mAtk" val="111.33"/>
            <mul stat="mAtkSpd" val="1.056"/>
            <add stat="accCombat" val="3.74"/>
        </for>
    </option>
    <option id="24323" name="o_w_84_2s_76">
        <!--M. Atk. increases by 111.33. Casting Speed increases by 5.6%-->
        <for>
            <add stat="mAtk" val="111.33"/>
            <mul stat="mAtkSpd" val="1.056"/>
            <add stat="critRate" val="17.6"/>
        </for>
    </option>
    <option id="24324" name="o_w_84_2s_77">
        <!---->
        <for>
            <add stat="regHp" val="3.08"/>
            <add stat="regMp" val="1.76"/>
        </for>
    </option>
    <option id="24325" name="o_w_84_2s_78">
        <!---->
        <for>
            <add stat="regHp" val="3.08"/>
            <add stat="regCp" val="2.74"/>
        </for>
    </option>
    <option id="24326" name="o_w_84_2s_79">
        <!---->
        <for>
            <add stat="regHp" val="3.08"/>
            <add stat="rEvas" val="4.675"/>
        </for>
    </option>
    <option id="24327" name="o_w_84_2s_80">
        <!---->
        <for>
            <add stat="regHp" val="3.08"/>
            <add stat="accCombat" val="3.74"/>
        </for>
    </option>
    <option id="24328" name="o_w_84_2s_81">
        <!---->
        <for>
            <add stat="regHp" val="3.08"/>
            <add stat="critRate" val="17.6"/>
        </for>
    </option>
    <option id="24329" name="o_w_84_2s_82">
        <!---->
        <for>
            <add stat="regMp" val="1.98"/>
            <add stat="regCp" val="2.74"/>
        </for>
    </option>
    <option id="24330" name="o_w_84_2s_83">
        <!---->
        <for>
            <add stat="regMp" val="1.98"/>
            <add stat="rEvas" val="4.675"/>
        </for>
    </option>
    <option id="24331" name="o_w_84_2s_84">
        <!---->
        <for>
            <add stat="regMp" val="1.98"/>
            <add stat="accCombat" val="3.74"/>
        </for>
    </option>
    <option id="24332" name="o_w_84_2s_85">
        <!---->
        <for>
            <add stat="regMp" val="1.98"/>
            <add stat="critRate" val="17.6"/>
        </for>
    </option>
    <option id="24333" name="o_w_84_2s_86">
        <!---->
        <for>
            <add stat="regCp" val="3.08"/>
            <add stat="rEvas" val="4.675"/>
        </for>
    </option>
    <option id="24334" name="o_w_84_2s_87">
        <!---->
        <for>
            <add stat="regCp" val="3.08"/>
            <add stat="accCombat" val="3.74"/>
        </for>
    </option>
    <option id="24335" name="o_w_84_2s_88">
        <!---->
        <for>
            <add stat="regCp" val="3.08"/>
            <add stat="critRate" val="17.6"/>
        </for>
    </option>
    <option id="24336" name="o_w_84_2s_89">
        <!---->
        <for>
            <add stat="rEvas" val="5.26"/>
            <add stat="accCombat" val="3.74"/>
        </for>
    </option>
    <option id="24337" name="o_w_84_2s_90">
        <!---->
        <for>
            <add stat="rEvas" val="5.26"/>
            <add stat="critRate" val="17.6"/>
        </for>
    </option>
    <option id="24338" name="o_w_84_2s_91">
        <!---->
        <for>
            <add stat="accCombat" val="4.208"/>
            <add stat="critRate" val="17.6"/>
        </for>
    </option>
    <option id="24339" name="o_w_84_2r_1">
        <!---->
        <for>
            <add stat="pDef" val="288.52"/>
        </for>
    </option>
    <option id="24340" name="o_w_84_2r_2">
        <!---->
        <for>
            <add stat="mDef" val="244.68"/>
        </for>
    </option>
    <option id="24341" name="o_w_84_2r_3">
        <!---->
        <for>
            <add stat="maxHp" val="526.8"/>
        </for>
    </option>
    <option id="24342" name="o_w_84_2r_4">
        <!---->
        <for>
            <add stat="maxMp" val="550.144"/>
        </for>
    </option>
    <option id="24343" name="o_w_84_2r_5">
        <!---->
        <for>
            <add stat="maxCp" val="691.425"/>
        </for>
    </option>
    <option id="24344" name="o_w_84_2r_6">
        <!--P. Atk. increases by 196.73. Attack Speed increases by 7.0%-->
        <for>
            <add stat="pAtk" val="196.73"/>
            <mul stat="pAtkSpd" val="1.070"/>
        </for>
    </option>
    <option id="24345" name="o_w_84_2r_7">
        <!--M. Atk. increases by 247.41. Casting Speed increases by 7.0%-->
        <for>
            <add stat="mAtk" val="247.41"/>
            <mul stat="mAtkSpd" val="1.070"/>
        </for>
    </option>
    <option id="24346" name="o_w_84_2r_8">
        <!---->
        <for>
            <add stat="regHp" val="6.86"/>
        </for>
    </option>
    <option id="24347" name="o_w_84_2r_9">
        <!---->
        <for>
            <add stat="regMp" val="4.42"/>
        </for>
    </option>
    <option id="24348" name="o_w_84_2r_10">
        <!---->
        <for>
            <add stat="regCp" val="6.86"/>
        </for>
    </option>
    <option id="24349" name="o_w_84_2r_11">
        <!---->
        <for>
            <add stat="rEvas" val="11.685"/>
        </for>
    </option>
    <option id="24350" name="o_w_84_2r_12">
        <!---->
        <for>
            <add stat="accCombat" val="9.348"/>
        </for>
    </option>
    <option id="24351" name="o_w_84_2r_13">
        <!---->
        <for>
            <add stat="critRate" val="44"/>
        </for>
    </option>
    <option id="24352" name="o_w_84_2r_14">
        <!---->
        <for>
            <add stat="pDef" val="144.26"/>
            <add stat="mDef" val="122.34"/>
        </for>
    </option>
    <option id="24353" name="o_w_84_2r_15">
        <!---->
        <for>
            <add stat="pDef" val="144.26"/>
            <add stat="maxHp" val="263.4"/>
        </for>
    </option>
    <option id="24354" name="o_w_84_2r_16">
        <!---->
        <for>
            <add stat="pDef" val="144.26"/>
            <add stat="maxMp" val="275.072"/>
        </for>
    </option>
    <option id="24355" name="o_w_84_2r_17">
        <!---->
        <for>
            <add stat="pDef" val="144.26"/>
            <add stat="maxCp" val="345.709"/>
        </for>
    </option>
    <option id="24356" name="o_w_84_2r_18">
        <!--P. Atk. increases by 98.36. Attack Speed increases by 4.9%-->
        <for>
            <add stat="pDef" val="144.26"/>
            <add stat="pAtk" val="98.36"/>
            <mul stat="pAtkSpd" val="1.049"/>
        </for>
    </option>
    <option id="24357" name="o_w_84_2r_19">
        <!--M. Atk. increases by 123.71. Casting Speed increases by 6.2%-->
        <for>
            <add stat="pDef" val="144.26"/>
            <add stat="mAtk" val="123.71"/>
            <mul stat="mAtkSpd" val="1.062"/>
        </for>
    </option>
    <option id="24358" name="o_w_84_2r_20">
        <!---->
        <for>
            <add stat="pDef" val="144.26"/>
            <add stat="regHp" val="3.42"/>
        </for>
    </option>
    <option id="24359" name="o_w_84_2r_21">
        <!---->
        <for>
            <add stat="pDef" val="144.26"/>
            <add stat="regMp" val="2.22"/>
        </for>
    </option>
    <option id="24360" name="o_w_84_2r_22">
        <!---->
        <for>
            <add stat="pDef" val="144.26"/>
            <add stat="regCp" val="3.42"/>
        </for>
    </option>
    <option id="24361" name="o_w_84_2r_23">
        <!---->
        <for>
            <add stat="pDef" val="144.26"/>
            <add stat="rEvas" val="5.845"/>
        </for>
    </option>
    <option id="24362" name="o_w_84_2r_24">
        <!---->
        <for>
            <add stat="pDef" val="144.26"/>
            <add stat="accCombat" val="4.676"/>
        </for>
    </option>
    <option id="24363" name="o_w_84_2r_25">
        <!---->
        <for>
            <add stat="pDef" val="144.26"/>
            <add stat="critRate" val="22"/>
        </for>
    </option>
    <option id="24364" name="o_w_84_2r_26">
        <!---->
        <for>
            <add stat="mDef" val="122.34"/>
            <add stat="maxHp" val="263.4"/>
        </for>
    </option>
    <option id="24365" name="o_w_84_2r_27">
        <!---->
        <for>
            <add stat="mDef" val="122.34"/>
            <add stat="maxMp" val="275.072"/>
        </for>
    </option>
    <option id="24366" name="o_w_84_2r_28">
        <!---->
        <for>
            <add stat="mDef" val="122.34"/>
            <add stat="maxCp" val="345.709"/>
        </for>
    </option>
    <option id="24367" name="o_w_84_2r_29">
        <!--P. Atk. increases by 98.36. Attack Speed increases by 4.9%-->
        <for>
            <add stat="mDef" val="122.34"/>
            <add stat="pAtk" val="98.36"/>
            <mul stat="pAtkSpd" val="1.049"/>
        </for>
    </option>
    <option id="24368" name="o_w_84_2r_30">
        <!--M. Atk. increases by 123.71. Casting Speed increases by 6.2%-->
        <for>
            <add stat="mDef" val="122.34"/>
            <add stat="mAtk" val="123.71"/>
            <mul stat="mAtkSpd" val="1.062"/>
        </for>
    </option>
    <option id="24369" name="o_w_84_2r_31">
        <!---->
        <for>
            <add stat="mDef" val="122.34"/>
            <add stat="regHp" val="3.42"/>
        </for>
    </option>
    <option id="24370" name="o_w_84_2r_32">
        <!---->
        <for>
            <add stat="mDef" val="122.34"/>
            <add stat="regMp" val="2.22"/>
        </for>
    </option>
    <option id="24371" name="o_w_84_2r_33">
        <!---->
        <for>
            <add stat="mDef" val="122.34"/>
            <add stat="regCp" val="3.42"/>
        </for>
    </option>
    <option id="24372" name="o_w_84_2r_34">
        <!---->
        <for>
            <add stat="mDef" val="122.34"/>
            <add stat="rEvas" val="5.845"/>
        </for>
    </option>
    <option id="24373" name="o_w_84_2r_35">
        <!---->
        <for>
            <add stat="mDef" val="122.34"/>
            <add stat="accCombat" val="4.676"/>
        </for>
    </option>
    <option id="24374" name="o_w_84_2r_36">
        <!---->
        <for>
            <add stat="mDef" val="122.34"/>
            <add stat="critRate" val="22"/>
        </for>
    </option>
    <option id="24375" name="o_w_84_2r_37">
        <!---->
        <for>
            <add stat="maxHp" val="263.4"/>
            <add stat="maxMp" val="275.072"/>
        </for>
    </option>
    <option id="24376" name="o_w_84_2r_38">
        <!---->
        <for>
            <add stat="maxHp" val="263.4"/>
            <add stat="maxCp" val="345.709"/>
        </for>
    </option>
    <option id="24377" name="o_w_84_2r_39">
        <!--P. Atk. increases by 98.36. Attack Speed increases by 4.9%-->
        <for>
            <add stat="maxHp" val="263.4"/>
            <add stat="pAtk" val="98.36"/>
            <mul stat="pAtkSpd" val="1.049"/>
        </for>
    </option>
    <option id="24378" name="o_w_84_2r_40">
        <!--M. Atk. increases by 123.71. Casting Speed increases by 6.2%-->
        <for>
            <add stat="maxHp" val="263.4"/>
            <add stat="mAtk" val="123.71"/>
            <mul stat="mAtkSpd" val="1.062"/>
        </for>
    </option>
    <option id="24379" name="o_w_84_2r_41">
        <!---->
        <for>
            <add stat="maxHp" val="263.4"/>
            <add stat="regHp" val="3.42"/>
        </for>
    </option>
    <option id="24380" name="o_w_84_2r_42">
        <!---->
        <for>
            <add stat="maxHp" val="263.4"/>
            <add stat="regMp" val="2.22"/>
        </for>
    </option>
    <option id="24381" name="o_w_84_2r_43">
        <!---->
        <for>
            <add stat="maxHp" val="263.4"/>
            <add stat="regCp" val="3.42"/>
        </for>
    </option>
    <option id="24382" name="o_w_84_2r_44">
        <!---->
        <for>
            <add stat="maxHp" val="263.4"/>
            <add stat="rEvas" val="5.845"/>
        </for>
    </option>
    <option id="24383" name="o_w_84_2r_45">
        <!---->
        <for>
            <add stat="maxHp" val="263.4"/>
            <add stat="accCombat" val="4.676"/>
        </for>
    </option>
    <option id="24384" name="o_w_84_2r_46">
        <!---->
        <for>
            <add stat="maxHp" val="263.4"/>
            <add stat="critRate" val="22"/>
        </for>
    </option>
    <option id="24385" name="o_w_84_2r_47">
        <!---->
        <for>
            <add stat="maxMp" val="275.072"/>
            <add stat="maxCp" val="345.709"/>
        </for>
    </option>
    <option id="24386" name="o_w_84_2r_48">
        <!--P. Atk. increases by 98.36. Attack Speed increases by 4.9%-->
        <for>
            <add stat="maxMp" val="275.072"/>
            <add stat="pAtk" val="98.36"/>
            <mul stat="pAtkSpd" val="1.049"/>
        </for>
    </option>
    <option id="24387" name="o_w_84_2r_49">
        <!--M. Atk. increases by 123.71. Casting Speed increases by 6.2%-->
        <for>
            <add stat="maxMp" val="275.072"/>
            <add stat="mAtk" val="123.71"/>
            <mul stat="mAtkSpd" val="1.062"/>
        </for>
    </option>
    <option id="24388" name="o_w_84_2r_50">
        <!---->
        <for>
            <add stat="maxMp" val="275.072"/>
            <add stat="regHp" val="3.42"/>
        </for>
    </option>
    <option id="24389" name="o_w_84_2r_51">
        <!---->
        <for>
            <add stat="maxMp" val="275.072"/>
            <add stat="regMp" val="2.22"/>
        </for>
    </option>
    <option id="24390" name="o_w_84_2r_52">
        <!---->
        <for>
            <add stat="maxMp" val="275.072"/>
            <add stat="regCp" val="3.42"/>
        </for>
    </option>
    <option id="24391" name="o_w_84_2r_53">
        <!---->
        <for>
            <add stat="maxMp" val="275.072"/>
            <add stat="rEvas" val="5.845"/>
        </for>
    </option>
    <option id="24392" name="o_w_84_2r_54">
        <!---->
        <for>
            <add stat="maxMp" val="275.072"/>
            <add stat="accCombat" val="4.676"/>
        </for>
    </option>
    <option id="24393" name="o_w_84_2r_55">
        <!---->
        <for>
            <add stat="maxMp" val="275.072"/>
            <add stat="critRate" val="22"/>
        </for>
    </option>
    <option id="24394" name="o_w_84_2r_56">
        <!--P. Atk. increases by 98.36. Attack Speed increases by 4.9%-->
        <for>
            <add stat="maxCp" val="345.709"/>
            <add stat="pAtk" val="98.36"/>
            <mul stat="pAtkSpd" val="1.049"/>
        </for>
    </option>
    <option id="24395" name="o_w_84_2r_57">
        <!--M. Atk. increases by 123.71. Casting Speed increases by 6.2%-->
        <for>
            <add stat="maxCp" val="345.709"/>
            <add stat="mAtk" val="123.71"/>
            <mul stat="mAtkSpd" val="1.062"/>
        </for>
    </option>
    <option id="24396" name="o_w_84_2r_58">
        <!---->
        <for>
            <add stat="maxCp" val="345.709"/>
            <add stat="regHp" val="3.42"/>
        </for>
    </option>
    <option id="24397" name="o_w_84_2r_59">
        <!---->
        <for>
            <add stat="maxCp" val="345.709"/>
            <add stat="regMp" val="2.22"/>
        </for>
    </option>
    <option id="24398" name="o_w_84_2r_60">
        <!---->
        <for>
            <add stat="maxCp" val="345.709"/>
            <add stat="regCp" val="3.42"/>
        </for>
    </option>
    <option id="24399" name="o_w_84_2r_61">
        <!---->
        <for>
            <add stat="maxCp" val="345.709"/>
            <add stat="rEvas" val="5.845"/>
        </for>
    </option>
</list>